kctaskman/__init__.py
kctaskman/es.py
kctaskman/log.py
kctaskman/manager.py
kctaskman/scaler.py
kctaskman/store.py
kctaskman/util.py
kctaskman/worker.py
kctaskman-0.0.5.dist-info/METADATA
kctaskman-0.0.5.dist-info/WHEEL
kctaskman-0.0.5.dist-info/top_level.txt
kctaskman-0.0.5.dist-info/RECORD
