Metadata-Version: 2.1
Name: kctaskman
Version: 0.0.5
Summary: task manager
Home-page: https://git.n.xiaomi.com/bigdatakc/python-kctaskman/-/tree/master
Author: yinrong
Author-email: yinrong@xiaomi.com
License: UNKNOWN
Platform: UNKNOWN
Classifier: Programming Language :: Python :: 3
Classifier: License :: OSI Approved :: MIT License
Classifier: Operating System :: OS Independent
Requires-Python: >=3.6
